nunchakupackdep/_C.cpython-311-x86_64-linux-gnu.so
nunchakupackdep/__init__.py
nunchakupackdep/__version__.py
nunchakupackdep/test.py
nunchakupackdep/utils.py
nunchakupackdep/caching/__init__.py
nunchakupackdep/caching/utils.py
nunchakupackdep/caching/diffusers_adapters/__init__.py
nunchakupackdep/caching/diffusers_adapters/flux.py
nunchakupackdep/caching/diffusers_adapters/sana.py
nunchakupackdep/csrc/flux.h
nunchakupackdep/csrc/gemm.h
nunchakupackdep/csrc/gemm88.h
nunchakupackdep/csrc/module.h
nunchakupackdep/csrc/ops.h
nunchakupackdep/csrc/pybind.cpp
nunchakupackdep/csrc/sana.h
nunchakupackdep/csrc/utils.h
nunchakupackdep/lora/__init__.py
nunchakupackdep/lora/flux/__init__.py
nunchakupackdep/lora/flux/compose.py
nunchakupackdep/lora/flux/convert.py
nunchakupackdep/lora/flux/diffusers_converter.py
nunchakupackdep/lora/flux/nunchakupackdep_converter.py
nunchakupackdep/lora/flux/packer.py
nunchakupackdep/lora/flux/utils.py
nunchakupackdep/models/__init__.py
nunchakupackdep/models/safety_checker.py
nunchakupackdep/models/text_encoders/__init__.py
nunchakupackdep/models/text_encoders/linear.py
nunchakupackdep/models/text_encoders/t5_encoder.py
nunchakupackdep/models/text_encoders/tinychat_utils.py
nunchakupackdep/models/transformers/__init__.py
nunchakupackdep/models/transformers/transformer_flux.py
nunchakupackdep/models/transformers/transformer_sana.py
nunchakupackdep/models/transformers/utils.py
nunchakupackdep-0.2.2+torch2.6.dist-info/LICENCE.txt
nunchakupackdep-0.2.2+torch2.6.dist-info/METADATA
nunchakupackdep-0.2.2+torch2.6.dist-info/WHEEL
nunchakupackdep-0.2.2+torch2.6.dist-info/top_level.txt
nunchakupackdep-0.2.2+torch2.6.dist-info/RECORD
