Metadata-Version: 2.1
Name: nunchakupackdep
Version: 0.2.2
Requires-Python: >=3.10
License-File: LICENCE.txt
Requires-Dist: diffusers (>=0.32.2)
Requires-Dist: transformers
Requires-Dist: accelerate
Requires-Dist: sentencepiece
Requires-Dist: protobuf
Requires-Dist: huggingface-hub
